fbcli/__init__.py
fbcli/cli.py
fbcli/config.py
fbcli/commands/__init__.py
fbcli/commands/servers.py
fullbore_cli-0.1.5.dist-info/METADATA
fullbore_cli-0.1.5.dist-info/WHEEL
fullbore_cli-0.1.5.dist-info/entry_points.txt
fullbore_cli-0.1.5.dist-info/top_level.txt
fullbore_cli-0.1.5.dist-info/RECORD
