Metadata-Version: 2.4
Name: fullbore-cli
Version: 0.1.5
Summary: Full Bore CLI tool
Author: Full Bore
Author-email: Full Bore <ben@fullbore.com>
Requires-Python: >=3.7
Requires-Dist: typer[all]
Requires-Dist: geezer
